MANIFEST.in
README.md
__init.__.pc
processors.py
requirements-dev.txt
requirements.txt
setup.cfg
setup.py
tox.ini
openshift_event_analysis.egg-info/PKG-INFO
openshift_event_analysis.egg-info/SOURCES.txt
openshift_event_analysis.egg-info/dependency_links.txt
openshift_event_analysis.egg-info/requires.txt
openshift_event_analysis.egg-info/top_level.txt