Metadata-Version: 1.1
Name: openshift-event-analysis
Version: 0.4.0
Summary: Some basic Classes to be use with OpenShift and Apache Kafka
Home-page: https://gitlab.com/openshift-analytics/openshift_event_analysis
Author: Christoph Görn
Author-email: goern@redhat.com
License: GPLv3+
Keywords: openshift kubernetes event_stream analysis
Platform: UNKNOWN
Classifier: Development Status :: 4 - Beta
Classifier: Intended Audience :: Developers
Classifier: Environment :: Other Environment
Classifier: Topic :: Software Development :: Build Tools
Classifier: License :: OSI Approved :: GNU General Public License v3 or later (GPLv3+)
Classifier: Programming Language :: Python :: 3
Classifier: Programming Language :: Python :: 3.5
Classifier: Programming Language :: Python :: 3.6
